populllus-2.2.2.dist-info/METADATA
populllus-2.2.2.dist-info/RECORD
populllus-2.2.2.dist-info/WHEEL
populllus-2.2.2.dist-info/entry_points.txt
populllus-2.2.2.dist-info/top_level.txt
populus/__init__.py
populus/exceptions.py
populus/plugin.py
populus/project.py
populus/wait.py
populus/api/__init__.py
populus/api/compile_contracts.py
populus/api/deploy.py
populus/api/project.py
populus/api/upgrade.py
populus/api/utils.py
populus/assets/Greeter.lll
populus/assets/Greeter.lll.abi
populus/assets/Greeter.sol
populus/assets/config.v1.schema.json
populus/assets/config.v2.schema.json
populus/assets/config.v3.schema.json
populus/assets/config.v4.schema.json
populus/assets/config.v5.schema.json
populus/assets/config.v6.schema.json
populus/assets/config.v7.schema.json
populus/assets/contract-data.v1.schema.json
populus/assets/defaults.user.v7.config.json
populus/assets/defaults.v1.config.json
populus/assets/defaults.v2.config.json
populus/assets/defaults.v3.config.json
populus/assets/defaults.v4.config.json
populus/assets/defaults.v5.config.json
populus/assets/defaults.v6.config.json
populus/assets/defaults.v7.config.json
populus/assets/test_greeter.py
populus/assets/test_greeter_lll.py
populus/chain/__init__.py
populus/chain/base.py
populus/chain/external.py
populus/chain/geth.py
populus/chain/tester.py
populus/chain/testrpc.py
populus/cli/__init__.py
populus/cli/chain_cmd.py
populus/cli/compile_cmd.py
populus/cli/config_cmd.py
populus/cli/deploy_cmd.py
populus/cli/init_cmd.py
populus/cli/main.py
populus/cli/upgrade_cmd.py
populus/compilation/__init__.py
populus/compilation/backends/__init__.py
populus/compilation/backends/base.py
populus/compilation/backends/lll.py
populus/compilation/backends/solc_auto.py
populus/compilation/backends/solc_combined_json.py
populus/compilation/backends/solc_standard_json.py
populus/compilation/backends/viper.py
populus/config/__init__.py
populus/config/backend.py
populus/config/base.py
populus/config/chain.py
populus/config/compiler.py
populus/config/defaults.py
populus/config/helpers.py
populus/config/loading.py
populus/config/validation.py
