Metadata-Version: 2.1
Name: populllus
Version: 2.2.2
Summary: Ethereum Development Framework (fork for LLL)
Home-page: https://gitlab.com/veox/populllus
Author: UNKNOWN
Author-email: UNKNOWN
License: MIT
Keywords: ethereum pytest
Platform: UNKNOWN
Classifier: Development Status :: 2 - Pre-Alpha
Classifier: Intended Audience :: Developers
Classifier: License :: OSI Approved :: BSD License
Classifier: Natural Language :: English
Classifier: Programming Language :: Python :: 3
Classifier: Programming Language :: Python :: 3.3
Classifier: Programming Language :: Python :: 3.4
Classifier: Programming Language :: Python :: 3.5
Classifier: Programming Language :: Python :: 3.6
Classifier: Programming Language :: Python :: 3.7
Requires-Dist: anyconfig (>=0.7.0)
Requires-Dist: click (>=6.6)
Requires-Dist: cytoolz (>=0.8.2)
Requires-Dist: contextlib2 (>=0.5.4)
Requires-Dist: eth-testrpc (>=1.3.0)
Requires-Dist: eth-utils (<0.8,>=0.7.4)
Requires-Dist: jsonschema (>=2.5.1)
Requires-Dist: py-geth (>=1.9.0)
Requires-Dist: py-solc (>=1.2.0)
Requires-Dist: pylru (>=1.0.9)
Requires-Dist: pysha3 (!=1.0,>1.0.0,>=0.3)
Requires-Dist: pytest (!=3.3.0,>=2.7.2)
Requires-Dist: rlp (<1,>=0.6.0)
Requires-Dist: semantic-version (>=2.6.0)
Requires-Dist: toposort (>=1.4)
Requires-Dist: watchdog (>=0.8.3)
Requires-Dist: web3 (<4,>=3.16.5)
